{
  "_fv": 34,
  "_type": "tool",
  "definition": {
    "renderType": 0,
    "texture": "mystalium_shovel_texture",
    "customModelName": "Normal",
    "name": "Mystalium Shovel",
    "specialInfo": [],
    "creativeTab": {
      "value": "CUSTOM:UmbreoTools"
    },
    "toolType": "Spade",
    "harvestLevel": 6,
    "efficiency": 11.0,
    "attackSpeed": 1.0,
    "enchantability": 20,
    "damageVsEntity": 4.0,
    "usageCount": 4234,
    "blocksAffected": [],
    "hasGlow": false,
    "repairItems": [
      {
        "value": "CUSTOM:MystaliumIngot"
      }
    ],
    "immuneToFire": false,
    "stayInGridWhenCrafting": false,
    "damageOnCrafting": false
  }
}